README
setup.py
src/patience/__init__.py
src/patience/action.py
src/patience/configuration.py
src/patience/git.py
src/patience/main.py
src/patience/patience2html.py
src/patience/patience_search.py
src/patience/resources.py
src/patience/status_string.py
src/patience/structures.py
src/patience/subversion.py
src/patience/visualization.py
src/patience.egg-info/PKG-INFO
src/patience.egg-info/SOURCES.txt
src/patience.egg-info/dependency_links.txt
src/patience.egg-info/entry_points.txt
src/patience.egg-info/requires.txt
src/patience.egg-info/top_level.txt
src/patience/actions/__init__.py
src/patience/actions/branches.py
src/patience/actions/checkout.py
src/patience/actions/develop.py
src/patience/actions/fetch.py
src/patience/actions/fix_upstream.py
src/patience/actions/install.py
src/patience/actions/merge.py
src/patience/actions/push.py
src/patience/actions/status.py
src/patience/actions/status_branches.py
src/patience/actions/unittests.py
src/patience/utils/__init__.py
src/patience/utils/execute.py