Metadata-Version: 1.0
Name: patience
Version: 1.4.0
Summary: A command line tool for managing multiple git repositories.
Home-page: http://github.com/AndreaCensi/patience
Author: Andrea Censi
Author-email: censi@mit.edu
License: UNKNOWN
Platform: UNKNOWN
